my_deeptools_win/__init__.py
my_deeptools_win/__logging.py
my_deeptools_win/_cli.py
my_deeptools_win/_counter.py
my_deeptools_win/_error.py
my_deeptools_win/_spliter.py
my_deeptools_win/count_use_bed.py
my_deeptools_win/deep_tools_base_function.ipynb
my_deeptools_win/deeptools_bigwig.ipynb
my_deeptools_win/multi_process_test.py
my_deeptools_win/multi_test.py
my_deeptools_win/multi_test2.py
my_deeptools_win/pyproject.toml
my_deeptools_win/test.ipynb
my_deeptools_win/test_big_to_bigwig.py
my_deeptools_win/test_my_deeptools.py
my_deeptools_win/TRy_HASH.ipynb
my_deeptools_win-0.1.2.dist-info/entry_points.txt
my_deeptools_win-0.1.2.dist-info/WHEEL
my_deeptools_win-0.1.2.dist-info/METADATA
my_deeptools_win-0.1.2.dist-info/RECORD
